csv_to_sqlite.py
csv_to_sqlite-2.1.2.dist-info/entry_points.txt
csv_to_sqlite-2.1.2.dist-info/LICENSE.txt
csv_to_sqlite-2.1.2.dist-info/WHEEL
csv_to_sqlite-2.1.2.dist-info/METADATA
csv_to_sqlite-2.1.2.dist-info/RECORD
