Metadata-Version: 2.1
Name: csv-to-sqlite
Version: 2.1.2
Summary: A script that processes the input CSV files and copies them into a SQLite database.
Home-page: https://github.com/zblesk/csv-to-sqlite
Keywords: csv sqlite conversion copy tool
Author: Ladislav Benc
Author-email: ladislav.benc@proton.me
Requires-Python: >=3
Classifier: Development Status :: 5 - Production/Stable
Classifier: Environment :: Console
Classifier: Intended Audience :: Developers
Classifier: License :: OSI Approved :: MIT License
Classifier: Natural Language :: English
Classifier: Programming Language :: Python
Classifier: Programming Language :: Python :: 3.5
Classifier: Programming Language :: Python :: 3.6
Classifier: Programming Language :: Python :: 3.7
Classifier: Programming Language :: Python :: 3.8
Classifier: Topic :: Utilities
Requires-Dist: click
